stegastatter/__init__.py
stegastatter/bit_operations_utils.py
stegastatter/bpcs/bit_plane.py
stegastatter/bpcs/block_operations.py
stegastatter/bpcs/bpcs_image.py
stegastatter/bpcs/capacity.py
stegastatter/bpcs/core.py
stegastatter/bpcs/dimension_computing.py
stegastatter/bpcs/dynamic_prefixing.py
stegastatter/bpcs/embed.py
stegastatter/bpcs/extract.py
stegastatter/bpcs/initilization_vector.py
stegastatter/content_wrapper/aes_gcm.py
stegastatter/content_wrapper/reed_solomon.py
stegastatter/content_wrapper/seeded_shuffler.py
stegastatter/content_wrapper/wrapper.py
stegastatter/engine.py
stegastatter/errors.py
stegastatter/image_utils.py
stegastatter/lsb/lsb_image.py
stegastatter/steganalysis/bit_plane_slicing.py
stegastatter/steganalysis/get_diff.py
stegastatter-1.0.4.dist-info/LICENSE
stegastatter-1.0.4.dist-info/METADATA
stegastatter-1.0.4.dist-info/WHEEL
stegastatter-1.0.4.dist-info/RECORD
