Metadata-Version: 2.3
Name: Stegastatter
Version: 1.0.4
Summary: A steganography engine
Author: Jebbex1
Requires-Python: >=3.13
Classifier: Programming Language :: Python :: 3
Classifier: Programming Language :: Python :: 3.13
Requires-Dist: numpy (>=2.3.1,<3.0.0)
Requires-Dist: pillow (>=11.3.0,<12.0.0)
Requires-Dist: pycryptodome (>=3.23.0,<4.0.0)
Requires-Dist: reedsolo (>=1.7.0,<2.0.0)
